featurebyte/__init__.py
featurebyte/__main__.py
featurebyte/_overrides/__init__.py
featurebyte/_overrides/typechecked_override.py
featurebyte/api/__init__.py
featurebyte/api/accessor/__init__.py
featurebyte/api/accessor/databricks.py
featurebyte/api/aggregator/__init__.py
featurebyte/api/aggregator/asat_aggregator.py
featurebyte/api/aggregator/base_aggregator.py
featurebyte/api/aggregator/base_asat_aggregator.py
featurebyte/api/aggregator/forward_aggregator.py
featurebyte/api/aggregator/forward_asat_aggregator.py
featurebyte/api/aggregator/simple_aggregator.py
featurebyte/api/aggregator/util.py
featurebyte/api/aggregator/vector_validator.py
featurebyte/api/aggregator/window_aggregator.py
featurebyte/api/api_handler/base.py
featurebyte/api/api_handler/catalog.py
featurebyte/api/api_handler/feature.py
featurebyte/api/api_handler/feature_job_setting_analysis.py
featurebyte/api/api_handler/feature_list.py
featurebyte/api/api_handler/feature_namespace.py
featurebyte/api/api_handler/target_namespace.py
featurebyte/api/api_handler/user_defined_function.py
featurebyte/api/api_object.py
featurebyte/api/api_object_util.py
featurebyte/api/base_table.py
featurebyte/api/batch_feature_table.py
featurebyte/api/batch_request_table.py
featurebyte/api/catalog.py
featurebyte/api/catalog_decorator.py
featurebyte/api/catalog_get_by_id_mixin.py
featurebyte/api/change_view.py
featurebyte/api/context.py
featurebyte/api/credential.py
featurebyte/api/data_source.py
featurebyte/api/deployment.py
featurebyte/api/dimension_table.py
featurebyte/api/dimension_view.py
featurebyte/api/entity.py
featurebyte/api/event_table.py
featurebyte/api/event_view.py
featurebyte/api/feature.py
featurebyte/api/feature_group.py
featurebyte/api/feature_job.py
featurebyte/api/feature_job_setting_analysis.py
featurebyte/api/feature_list.py
featurebyte/api/feature_namespace.py
featurebyte/api/feature_or_target_mixin.py
featurebyte/api/feature_or_target_namespace_mixin.py
featurebyte/api/feature_store.py
featurebyte-3.3.1.dist-info/WHEEL
featurebyte-3.3.1.dist-info/METADATA
featurebyte-3.3.1.dist-info/RECORD
