Metadata-Version: 2.3
Name: featurebyte
Version: 3.3.1
Summary: Python Library for FeatureOps
Author: FeatureByte
Author-email: FeatureByte <it-admin@featurebyte.com>
License: Elastic License 2.0
Classifier: Development Status :: 5 - Production/Stable
Classifier: Intended Audience :: Developers
Classifier: Operating System :: OS Independent
Classifier: Topic :: Software Development :: Libraries :: Python Modules
Classifier: License :: Other/Proprietary License
Classifier: Programming Language :: Python :: 3
Classifier: Programming Language :: Python :: 3.10
Classifier: Programming Language :: Python :: 3.11
Classifier: Programming Language :: Python :: 3.12
Requires-Dist: aiofiles>=24
Requires-Dist: alive-progress>=3
Requires-Dist: black>=24
Requires-Dist: cachetools>=5
Requires-Dist: croniter>=5
Requires-Dist: cryptography>=45
Requires-Dist: grapheme>=0.6
Requires-Dist: humanize>=4
Requires-Dist: importlib-metadata>=8
Requires-Dist: jinja2>=3
Requires-Dist: lazy-object-proxy>=1
Requires-Dist: numpy
Requires-Dist: orjson>=3
Requires-Dist: pandas>=2
Requires-Dist: pillow>=10
Requires-Dist: pyarrow>=18
Requires-Dist: pydantic-extra-types>=2
Requires-Dist: pydantic-settings>=2
Requires-Dist: pydantic~=2.8
Requires-Dist: pymongo>=4
Requires-Dist: pyopenssl>=23
Requires-Dist: python-multipart
Requires-Dist: python-on-whales
Requires-Dist: pyyaml>=5
Requires-Dist: requests>=2
Requires-Dist: rich>=13
Requires-Dist: sqlglot~=25.0
Requires-Dist: typeguard>=4
Requires-Dist: typer
Requires-Dist: websocket-client>=1
Requires-Dist: aioboto3 ; extra == 'server'
Requires-Dist: asyncache ; extra == 'server'
Requires-Dist: celery[redis] ; extra == 'server'
Requires-Dist: celerybeat-mongo ; extra == 'server'
Requires-Dist: databricks-sdk ; extra == 'server'
Requires-Dist: databricks-sql-connector~=4.0.0 ; extra == 'server'
Requires-Dist: fastapi ; extra == 'server'
Requires-Dist: feast[snowflake,redis,mysql,gcp]==0.40.1 ; extra == 'server'
Requires-Dist: featurebyte-freeware ; extra == 'server'
Requires-Dist: gevent ; extra == 'server'
Requires-Dist: google-cloud-bigquery ; extra == 'server'
Requires-Dist: google-cloud-bigquery-storage ; extra == 'server'
Requires-Dist: motor ; extra == 'server'
Requires-Dist: weasyprint ; extra == 'server'
Requires-Dist: pyhive[hive-pure-sasl] ; extra == 'server'
Requires-Dist: redis ; extra == 'server'
Requires-Dist: requests-kerberos ; extra == 'server'
Requires-Dist: smart-open[azure,gcs] ; extra == 'server'
Requires-Dist: snowflake-connector-python ; extra == 'server'
Requires-Dist: thrift-sasl ; extra == 'server'
Requires-Dist: uvicorn[standard] ; extra == 'server'
Requires-Python: >=3.10
Provides-Extra: server
